timeseriestools/__init__.py
timeseriestools/timeseriestools.py
timeseriestools-0.0.2.dist-info/METADATA
timeseriestools-0.0.2.dist-info/WHEEL
timeseriestools-0.0.2.dist-info/RECORD
