Metadata-Version: 2.1
Name: timeseriestools
Version: 0.0.2
Summary: Create Tearsheets with timeseries.tools
Project-URL: Homepage, https://timeseries.tools
Classifier: Operating System :: OS Independent
Classifier: Programming Language :: Python :: 3
Requires-Python: >=3.7
Requires-Dist: pandas
Requires-Dist: requests
